{
    "name": "LEDBlue5v",
    "category": [
        "output"
    ],
    "blockId": "!11372",
    "coders": [
        "LEDBlue"
    ],
    "supportedControllers": [
        "ATMega328P",
        "ArduinoLeonardo",
        "ArduinoMega",
        "ArduinoMicro",
        "ArduinoNano",
        "ArduinoProMini5v",
        "ArduinoUno",
        "ATTiny85",
        "Teensy32"
    ],
    "parts": [
        {
            "name": "this",
            "part": "LEDBlue",
            "properties": "Blue (470nm)"
        },
        {
            "name": "Res1",
            "part": "Res100O"
        }
    ],
    "wires": [
        {
            "from": "this.Gnd",
            "to": "Res1.con1"
        },
        {
            "from": "Res1.con0",
            "to": "GND"
        }
    ],
    "ports": [
        {
            "name": "Vin",
            "interface": {
                "requires":[[0,["5v","PWM"]]],
                "unique": true
            }
        },
        {
            "name": "GND",
            "interface": {
                "requires":[[0,["GND"]]]
            }
        }
    ]
}