{
  "name": "PotentiometerSoft",
  "supportedControllers": [
    "ATMega328P",
    "ArduinoGemma",
    "ArduinoLeonardo",
    "ArduinoMega",
    "ArduinoMicro",
    "ArduinoNano",
    "ArduinoProMini3v3",
    "ArduinoProMini5v",
    "ArduinoUno",
    "ESP32DevKitC",
    "NodeMCU",
    "RPI3B",
    "Teensy32"
  ],
  "code": {
    "snippetCode": "int {{varname}}Val = {{varname}}.read();\nSerial.print(F(\"Val: \")); Serial.println({{varname}}Val);\n"
  },
  "license": "circuito",
  "instantiate": {
    "classname": "Potentiometer",
    "ports": [
      "wiper"
    ]
  },
  "files": [
    "Potentiometer.h",
    "Potentiometer.cpp",
    "Potentiometer_license.txt",
    "AnalogReader.h",
    "AnalogReader.cpp"
  ],
  "includeHeaders": [
    "Potentiometer.h"
  ]
}