{
    "name": "TiltSW",
    "supportedControllers": [
        "ATMega328P",
        "ArduinoLeonardo",
        "ArduinoMega",
        "ArduinoMicro",
        "ArduinoNano",
        "ArduinoProMini3v3",
        "ArduinoProMini5v",
        "ArduinoUno",
        "ESP32DevKitC",
        "NodeMCU",
        "RPI3B"
    ],
    "code": {},
    "license": "circuito",
    "instantiate": {
        "classname": "Button",
        "ports": [
            "2"
        ],
        "varname": "TiltSwitch"
    },
    "files": [
        "../Global/lib/Button.h",
        "../Global/lib/Button.cpp",
        "../Global/lib/Button_license.txt"
    ],
    "includeHeaders": []
}