{
    "name": "74HC4051",
    "symbol": {
        "ref": "circuito_74HC4051E.svg",
        "URL": "https://res.cloudinary.com/circuito/image/upload/dvt5h9uo3e55twps7yqs"
    },
    "displayName": "74HC4051 - Analog Multiplexer and Demultiplexer",
    "category": [
        "support"
    ],
    "desc": "digitally controlled analog switches using CMOS technology.<br>This analog multiplexer and demultiplexer control analog voltages that may vary across the voltage supply range.<br>It consists of bidirectional switches that allow any analog input to be used as an output and vice versa. ",
    "bom": [
        {
            "name": "octopart",
            "image": "https://res.cloudinary.com/circuito/image/upload/x8izr94mpjh4r9yzucvl",
            "link": "https://octopart.com/cd74hc4051e-texas+instruments-43489",
            "price": "0.6",
            "SKU": "296-12810-5-ND"
        }
    ],
    "info": {
        "setup": "The small dot on the chip indicates pin number 1, use it to set the orientation.",
        "test": ""
    },
    "placing": {
        "onBreadboard": true
    }
}