{
    "name": "ADXL345",
    "symbol": {
        "ref": "circuito_ADXL345.svg",
        "URL": "https://ucarecdn.com/f0a44d07-6d94-4007-91fb-af3cd946dd66/"
    },
    "displayName": "SparkFun ADXL345 - Triple Axis Accelerometer Breakout",
    "category": [
        "input"
    ],
    "desc": "",
    "bom": [
        {
            "name": "octopart",
            "image": "https://ucarecdn.com/bf24de74-81e8-4559-ae8b-19ed29bc9426/",
            "link": "https://octopart.com/sen-09836-sparkfun-55832357",
            "price": "17.95",
            "SKU": "1568-1035-ND"
        }
    ],
    "info": {
        "setup": "",
        "test": "Move the sensor to see the values change"
    },
    "headers": [
        8,
        "MaleHeaders"
    ],
    "placing": {
        "onBreadboard": false
    }
}