{
  "name": "AM2302",
  "symbol": "http://res.cloudinary.com/circuito/image/upload/client/circuito_am2302_wcrxww",
  "displayName": "AM2302 Humidity and Temperature Sensor",
  "category": [
    "input"
  ],
  "desc": "",
  "bom": [
    {
      "name": "octopart",
      "image": "http://res.cloudinary.com/circuito/image/upload/client/OP_0280s_qoqpqo",
      "link": "https://octopart.com/393-adafruit+industries-32978581",
      "price": "15.00",
      "SKU": "1528-1229-ND"
    }
  ],
  "info": {
    "setup": "",
    "test": "blow air on the sensor to see its readings change"
  },
  "placing": {
    "onBreadboard": false
  }
}