{
    "name": "GUVA-S12SD",
    "symbol": {
        "ref": "circuito_Analog UV Light Sensor Breakout - GUVA-S12SD.svg",
        "URL": "http://res.cloudinary.com/circuito/image/upload/fuxlrdjybtlqvbg03l2z"
    },
    "displayName": "GUVA-S12SD - Analog UV Light Sensor Breakout",
    "category": [
        "input"
    ],
    "desc": "",
    "bom": [
        {
            "name": "octopart",
            "image": "http://res.cloudinary.com/circuito/image/upload/vrzxqbgxdmieowdtwski",
            "link": "https://octopart.com/1918-adafruit+industries-53099572",
            "price": "6.5",
            "SKU": "1528-1468-ND"
        }
    ],
    "info": {
        "setup": "",
        "test": "Test is using module by using A UV tanning lamp rather than an IR LED."
    },
    "placing": {
        "onBreadboard": true
    }
}