{
    "name": "IRLineFollowArray",
    "symbol": {
        "ref": "circuito_IR Array.svg",
        "URL": "http://res.cloudinary.com/circuito/image/upload/ikzw7pii0hgq2rmpq2nf"
    },
    "displayName": "SparkFun Line Follower Array",
    "category": [
        "input"
    ],
    "desc": "",
    "bom": [
        {
            "name": "octopart",
            "image": "http://res.cloudinary.com/circuito/image/upload/vfiqziyjftlm0zzlpi2j",
            "link": "https://octopart.com/sen-13582-sparkfun-66784744",
            "price": "29.95",
            "SKU": "1568-1646-ND",
            "headers": [
                6,
                "MaleHeaders"
            ]
        }
    ],
    "info": {
        "setup": "",
        "test": ""
    },
    "placing": {
        "onBreadboard": false
    }
}