{
    "name": "JoystickSFBreakout",
    "symbol": {
        "ref": ""
    },
    "displayName": "SparkFun Thumb Joystick Breakout",
    "category": [
        "support"
    ],
    "desc": "",
    "bom": [
        {
            "name": "octopart",
            "image": "http://res.cloudinary.com/circuito/image/upload/oyeljwyjp9skh24em1fc",
            "link": "https://octopart.com/bob-09110-sparkfun-22107485",
            "price": "1.95",
            "SKU": "1568-1791-ND"
        }
    ],
    "info": {
        "setup": "",
        "test": ""
    }
}