{
    "name": "MQ7_breakout_board",
    "symbol": {
        "ref": ""
    },
    "displayName": "Gas Sensor Breakout Board",
    "category": [
        "support"
    ],
    "desc": "This breakout board help connect the MQ sensors to a breaboard.",
    "bom": [
        {
            "name": "octopart",
            "image": "https://res.cloudinary.com/circuito/image/upload/vsw7cifpmgvjzh8fdxbt",
            "link": "https://octopart.com/bob-08891-sparkfun-22107481",
            "price": "0.95",
            "SKU": "1568-1378-ND"
        }
    ],
    "info": {
        "setup": "",
        "test": ""
    }
}