{
  "name": "AM2302",
  "category": [
    "input"
  ],
  "blockId": "963780",
  "app": {
    "appName": "AM2302 Digital Temperature and Humidity Sensor",
    "image": "http://res.cloudinary.com/circuito/image/upload/nqhyrltgv1knwcztk3it",
    "numericName": "AM2302",
    "shortName": "Temperature and Humidity Sensor",
    "indicators": {
      "verified": false,
      "solder": true
    },
    "desc": "<p>Simple I2C Digital Humidity and Temperature sensor, 2-5% humidity accuracy and 0.5C temperature accuracy.</p>",
    "visible": true
  },
  "circuits": [
    {
      "name": "5v",
      "coders": [
        "AM2302"
      ],
      "supportedControllers": [
        "ATMega328P",
        "ArduinoLeonardo",
        "ArduinoMega",
        "ArduinoMicro",
        "ArduinoNano",
        "ArduinoProMini5v",
        "ArduinoUno"
      ],
      "parts": [
        {
          "name": "this",
          "part": "AM2302"
        }
      ],
      "wires": [],
      "ports": [
        {
          "name": "GND",
          "interface": {
            "requires": [
              {
                "cost": 0,
                "spec": "",
                "voltage": "GND"
              }
            ],
            "portType": "requires"
          }
        },
        {
          "name": "VCC",
          "interface": {
            "requires": [
              {
                "cost": 0,
                "spec": "",
                "voltage": "5v"
              }
            ],
            "portType": "requires"
          }
        },
        {
          "name": "SIG",
          "interface": {
            "requires": [
              {
                "cost": 0,
                "spec": "DigitalIn",
                "voltage": "5v"
              }
            ],
            "unique": true,
            "portType": "requires"
          },
          "includeInFirmware": true
        }
      ],
      "priority": 0
    },
    {
      "name": "3v3",
      "coders": [
        "AM2302"
      ],
      "supportedControllers": [
        "ArduinoGemma",
        "ArduinoProMini3v3",
        "ESP32DevKitC",
        "NodeMCU",
        "RPI3B",
        "Teensy32"
      ],
      "parts": [
        {
          "name": "this",
          "part": "AM2302"
        }
      ],
      "wires": [],
      "ports": [
        {
          "name": "GND",
          "interface": {
            "requires": [
              {
                "cost": 0,
                "spec": "",
                "voltage": "GND"
              }
            ],
            "portType": "requires"
          }
        },
        {
          "name": "VCC",
          "interface": {
            "requires": [
              {
                "cost": 0,
                "spec": "",
                "voltage": "3.3v"
              }
            ],
            "portType": "requires"
          }
        },
        {
          "name": "SIG",
          "interface": {
            "requires": [
              {
                "cost": 0,
                "spec": "DigitalIn",
                "voltage": "3.3v"
              }
            ],
            "unique": true,
            "portType": "requires"
          },
          "includeInFirmware": true
        }
      ],
      "priority": 1
    }
  ]
}