{
    "name": "MicroSwitch",
    "category": [
        "input"
    ],
    "blockId": "305155",
    "app": {
        "appName": "Micro Switch",
        "image": "http://res.cloudinary.com/circuito/image/upload/x8knpjlz9ychdknf2jif",
        "numericName": "",
        "shortName": "Micro Switch",
        "tags": [
            "inputs"
        ],
        "indicators": {
            "verified": "true",
            "code": "true",
            "solder": "false"
        },
        "desc": "<p>Micro-switches are really handy in any kind of project, it actuated by very little physical force, it\u2019s reliable, cheap, and comes in many sizes and shapes. It actually acts as a small push button, and have a \u2018clicky\u2019 sound and a nice tactile feel.<br><a class=\"more-info\" target=\"_blank\" href=\"https://www.circuito.io/component/micro-switch/\">Learn More</a></p>",
        "visible": "False"
    },
    "circuits": [
        {
            "name": "MicroSwitch5v",
            "coders": [
                "MicroSwitch"
            ],
            "supportedControllers": [
                "ATMega328P",
                "ArduinoLeonardo",
                "ArduinoMega",
                "ArduinoMicro",
                "ArduinoNano",
                "ArduinoProMini5v",
                "ArduinoUno",
                "ATTiny85",
                "Teensy32"
            ],
            "parts": [
                {
                    "name": "this",
                    "part": "MicroSwitch"
                },
                {
                    "name": "r1",
                    "part": "Res10KO"
                }
            ],
            "wires": [
                {
                    "from": "this.COM",
                    "to": "r1.con0"
                },
                {
                    "from": "r1.con1",
                    "to": "0"
                }
            ],
            "ports": [
                {
                    "name": "NO",
                    "interface": {
                        "requires":[[0,["5v"]]]
                    }
                },
                {
                    "name": "0",
                    "interface": {
                        "requires":[[0,["GND"]]]
                    }
                },
                {
                    "name": "COM",
                    "interface": {
                        "requires":[[0,["5v","DigitalIn"]]],
                        "unique": true
                    }
                }
            ],
            "priority": 0
        },
        {
            "name": "MicroSwitch3v3",
            "coders": [
                "MicroSwitch"
            ],
            "supportedControllers": [
                "ArduinoGemma",
                "ArduinoProMini3v3",
                "ESP32DevKitC",
                "NodeMCU",
                "RPI3B",
                "ATTiny85",
                "Teensy32"
            ],
            "parts": [
                {
                    "name": "this",
                    "part": "MicroSwitch"
                },
                {
                    "name": "r1",
                    "part": "Res10KO"
                }
            ],
            "wires": [
                {
                    "from": "this.COM",
                    "to": "r1.con0"
                },
                {
                    "from": "r1.con1",
                    "to": "0"
                }
            ],
            "ports": [
                {
                    "name": "NO",
                    "interface": {
                        "requires":[[0,["3.3v"]]]
                    }
                },
                {
                    "name": "0",
                    "interface": {
                        "requires":[[0,["GND"]]]
                    }
                },
                {
                    "name": "COM",
                    "interface": {
                        "requires":[[0,["3.3v","DigitalIn"]]],
                        "unique": true
                    }
                }
            ],
            "priority": 1
        }
    ]
}