{
    "name": "PotentiometerTrim5v",
    "path": "PotentiometerTrim",
    "category": "input",
    "blockId": "!172542",
    "coders": [
        "PotentiometerTrim"
    ],
    "supportedControllers": [
        "ATMega328P",
        "ArduinoLeonardo",
        "ArduinoMega",
        "ArduinoMicro",
        "ArduinoNano",
        "ArduinoProMini5v",
        "ArduinoUno"
    ],
    "circuit": {
        "parts": [
            {
                "name": "this",
                "part": "PotentiometerTrim"
            }
        ],
        "ports": [
            {
                "name": "GND",
                "interface": {
                    "requires":[[0,["GND"]]]
                }
            },
            {
                "name": "SIG",
                "interface": {
                    "requires":[[0,["ADC"]]],
                    "unique": true
                }
            },
            {
                "name": "VDD",
                "interface": {
                    "requires":[[1,["5v"]]]
                }
            },
            {
                "name": "supportedControllers",
                "interface": {
                    "requires":[[0,["ArduinoMega"]],[1,["ArduinoUno"]],[2,["ArduinoMicro"]],[3,["ArduinoProMini5v"]],[7,["ArduinoLeonardo"]],[8,["ArduinoNano"]],[9,["ATMega328P"]]]
                }
            }
        ]
    }
}