{
  "name": "TiltSW",
  "category": [
    "input"
  ],
  "blockId": "10289",
  "app": {
    "appName": "Tilt Sensor - AT407",
    "image": "http://res.cloudinary.com/circuito/image/upload/aaoybkoqlqooypgsxo6g",
    "numericName": "AT407",
    "shortName": "Tilt Sensor",
    "indicators": {
      "verified": true,
      "solder": false
    },
    "desc": "<p>A basic tilt switch. It can be used to detect if a device is flipped. </p>",
    "visible": true
  },
  "circuits": [
    {
      "name": "5v",
      "coders": [
        "TiltSW"
      ],
      "supportedControllers": [
        "ATMega328P",
        "ArduinoLeonardo",
        "ArduinoMega",
        "ArduinoMicro",
        "ArduinoNano",
        "ArduinoProMini5v",
        "ArduinoUno",
        "ATTiny85",
        "Teensy32"
      ],
      "parts": [
        {
          "name": "this",
          "part": "TiltSW"
        },
        {
          "name": "r1",
          "part": "Res10KO"
        }
      ],
      "wires": [
        {
          "from": "this.2",
          "to": "r1.con0"
        },
        {
          "from": "r1.con1",
          "to": "0"
        }
      ],
      "ports": [
        {
          "name": "0",
          "interface": {
            "requires": [
              {
                "cost": 0,
                "spec": "",
                "voltage": "GND"
              }
            ]
          }
        },
        {
          "name": "1",
          "interface": {
            "requires": [
              {
                "cost": 0,
                "spec": "",
                "voltage": "5v"
              }
            ]
          }
        },
        {
          "name": "2",
          "interface": {
            "requires": [
              {
                "cost": 0,
                "spec": "DigitalIn",
                "voltage": "5v"
              }
            ],
            "unique": true
          },
          "includeInFirmware": true
        }
      ],
      "priority": 0
    },
    {
      "name": "3v3",
      "coders": [
        "TiltSW"
      ],
      "supportedControllers": [
        "ArduinoProMini3v3",
        "ESP32DevKitC",
        "NodeMCU",
        "RPI3B",
        "ATTiny85",
        "Teensy32"
      ],
      "parts": [
        {
          "name": "this",
          "part": "TiltSW"
        },
        {
          "name": "r1",
          "part": "Res10KO"
        }
      ],
      "wires": [
        {
          "from": "this.2",
          "to": "r1.con0"
        },
        {
          "from": "r1.con1",
          "to": "0"
        }
      ],
      "ports": [
        {
          "name": "0",
          "interface": {
            "requires": [
              {
                "cost": 0,
                "spec": "",
                "voltage": "GND"
              }
            ]
          }
        },
        {
          "name": "1",
          "interface": {
            "requires": [
              {
                "cost": 0,
                "spec": "",
                "voltage": "3.3v"
              }
            ]
          }
        },
        {
          "name": "2",
          "interface": {
            "requires": [
              {
                "cost": 0,
                "spec": "DigitalIn",
                "voltage": "3.3v"
              }
            ],
            "unique": true
          },
          "includeInFirmware": true
        }
      ],
      "priority": 1
    }
  ]
}